sinnia_shared/__init__.py
sinnia_shared/amqp.py
sinnia_shared/string_utils.py
sinnia_shared/timezones.py
sinnia_shared/utils.py
sinnia_shared-0.3.0.dist-info/METADATA
sinnia_shared-0.3.0.dist-info/WHEEL
sinnia_shared-0.3.0.dist-info/RECORD
