Metadata-Version: 2.1
Name: sinnia-shared
Version: 0.3.0
Summary: AMQP utils. Named database connection utils. String and date utils.
Author: soniaseguz
Author-email: sonia.segura@sinnia.com
Requires-Python: >=3.9,<4.0
Classifier: Programming Language :: Python :: 3
Classifier: Programming Language :: Python :: 3.9
Classifier: Programming Language :: Python :: 3.10
Classifier: Programming Language :: Python :: 3.11
Requires-Dist: pymysql (>=1.1.0,<2.0.0)
